alligator/__init__.py
alligator/backends/__init__.py
alligator/backends/locmem_backend.py
alligator/backends/redis_backend.py
alligator/backends/sqlite_backend.py
alligator/backends/sqs_backend.py
alligator/constants.py
alligator/exceptions.py
alligator/gator.py
alligator/tasks.py
alligator/utils.py
alligator/workers.py
alligator-1.0.0.dist-info/entry_points.txt
alligator-1.0.0.dist-info/LICENSE
alligator-1.0.0.dist-info/WHEEL
alligator-1.0.0.dist-info/METADATA
alligator-1.0.0.dist-info/RECORD
