Metadata-Version: 2.1
Name: alligator
Version: 1.0.0
Summary: Simple offline task queues.
Home-page: https://github.com/toastdriven/alligator
License: BSD-3-Clause
Keywords: queues,tasks,offline
Author: Daniel Lindsley
Author-email: daniel@toastdriven.com
Requires-Python: >=3.6,<4.0
Classifier: License :: OSI Approved :: BSD License
Classifier: Programming Language :: Python :: 3
Classifier: Programming Language :: Python :: 3.6
Classifier: Programming Language :: Python :: 3.7
Classifier: Programming Language :: Python :: 3.8
Project-URL: Documentation, https://alligator.readthedocs.io/en/latest/
Project-URL: Repository, https://github.com/toastdriven/alligator
